{
    "$schema": "http://schema.management.azure.com/schemas/2015-01-01/deploymentTemplate.json#",
    "contentVersion": "1.0.0.0",
    "parameters": {
        "dnsZoneName": {
            "type": "string"
        },
        "principalId": {
            "metadata": {
                "description": "Object id of service principal."
            },
            "type": "string"
        }
    },
    "resources": [
        {
            "apiVersion": "2016-04-01",
            "type": "Microsoft.Network/dnsZones",
            "name": "[parameters('dnsZoneName')]",
            "location": "global",
            "dependsOn": [],
            "tags": {},
            "properties": {}
        },
        {
            "type": "Microsoft.Network/dnsZones/providers/roleAssignments",
            "apiVersion": "2018-09-01-preview",
            "name": "[concat(parameters('dnsZoneName'), '/Microsoft.Authorization/', guid(parameters('dnsZoneName'), parameters('principalId')))]",
            "dependsOn": [
                "[parameters('dnsZoneName')]"
            ],
            "properties": {
                "roleDefinitionId": "[concat('/subscriptions/', subscription().subscriptionId, '/providers/Microsoft.Authorization/roleDefinitions/', 'befefa01-2a29-4197-83a8-272ff33ce314')]",
                "principalId": "[parameters('principalId')]"
            }
        },
        {
            "type": "Microsoft.Authorization/roleAssignments",
            "apiVersion": "2018-09-01-preview",
            "name": "[guid(resourceGroup().id)]",
            "dependsOn": [
                "[parameters('dnsZoneName')]"
            ],
            "properties": {
                "roleDefinitionId": "[concat('/subscriptions/', subscription().subscriptionId, '/providers/Microsoft.Authorization/roleDefinitions/', 'acdd72a7-3385-48ef-bd42-f606fba81ae7')]",
                "principalId": "[parameters('principalId')]"
            }
        },
        {
            "type": "Microsoft.Network/dnszones/CAA",
            "apiVersion": "2018-05-01",
            "name": "[concat(parameters('dnsZoneName'), '/@')]",
            "dependsOn": [
                "[resourceId('Microsoft.Network/dnszones', parameters('dnsZoneName'))]"
            ],
            "properties": {
                "TTL": 3600,
                "caaRecords": [
                    {
                        "flags": 0,
                        "tag": "issue",
                        "value": "letsencrypt.org"
                    }
                ],
                "targetResource": {}
            }
        }
    ]
}